commonfate_provider/__init__.py
commonfate_provider/access.py
commonfate_provider/cli/__init__.py
commonfate_provider/cli/main.py
commonfate_provider/config/__init__.py
commonfate_provider/config/loaders.py
commonfate_provider/config/tests/test_configurer.py
commonfate_provider/config/tests/test_loaders.py
commonfate_provider/dataclass.py
commonfate_provider/diagnostics.py
commonfate_provider/health.py
commonfate_provider/namespace.py
commonfate_provider/provider.py
commonfate_provider/resources.py
commonfate_provider/rpc.py
commonfate_provider/runtime/__init__.py
commonfate_provider/runtime/aws_lambda.py
commonfate_provider/runtime/aws_lambda_entrypoint.py
commonfate_provider/runtime/initialise.py
commonfate_provider/runtime/tests/__init__.py
commonfate_provider/runtime/tests/__snapshots__/aws_lambda_test/test_grant_works.json
commonfate_provider/runtime/tests/__snapshots__/aws_lambda_test/test_load_works.json
commonfate_provider/runtime/tests/__snapshots__/aws_lambda_test/test_load_works_with_subtasks.json
commonfate_provider/runtime/tests/__snapshots__/aws_lambda_test/test_provider_describe.json
commonfate_provider/runtime/tests/__snapshots__/aws_lambda_test/test_provider_describe_with_config.json
commonfate_provider/runtime/tests/__snapshots__/aws_lambda_test/test_provider_describe_with_errors.json
commonfate_provider/runtime/tests/__snapshots__/aws_lambda_test/test_provider_describe_with_resources.json
commonfate_provider/runtime/tests/aws_lambda_entrypoint_test.py
commonfate_provider/runtime/tests/aws_lambda_test.py
commonfate_provider/runtime/tests/commonfate_provider_dist/README.md
commonfate_provider/runtime/tests/commonfate_provider_dist/__init__.py
commonfate_provider/runtime/tests/commonfate_provider_dist/manifest.json
commonfate_provider/runtime/tests/commonfate_provider_dist/provider.py
commonfate_provider/runtime/tests/initialise_test.py
commonfate_provider/schema.py
commonfate_provider/target.py
commonfate_provider/tasks.py
commonfate_provider-0.9.2.dist-info/METADATA
commonfate_provider-0.9.2.dist-info/WHEEL
commonfate_provider-0.9.2.dist-info/entry_points.txt
commonfate_provider-0.9.2.dist-info/RECORD
