Metadata-Version: 2.1
Name: commonfate-provider
Version: 0.9.2
Summary: Python Provider Development kit
Author: Chris Norman
Author-email: chris@commonfate.io
Requires-Python: >=3.9,<4.0
Classifier: Programming Language :: Python :: 3
Classifier: Programming Language :: Python :: 3.9
Classifier: Programming Language :: Python :: 3.10
Classifier: Programming Language :: Python :: 3.11
Requires-Dist: boto3 (>=1.26.82,<2.0.0)
Requires-Dist: click (>=8.1.3,<9.0.0)
Requires-Dist: common-fate-schema (>=0.7.0,<0.8.0)
Requires-Dist: pydantic (>=1.10.5,<2.0.0)
Requires-Dist: toml (==0.10.2)
Requires-Dist: typing-extensions (>=4.5.0,<5.0.0)
